dataclasses_avroschema/__init__.py
dataclasses_avroschema/case.py
dataclasses_avroschema/dacite_config.py
dataclasses_avroschema/exceptions.py
dataclasses_avroschema/faker.py
dataclasses_avroschema/faust/__init__.py
dataclasses_avroschema/faust/main.py
dataclasses_avroschema/faust/parser.py
dataclasses_avroschema/fields/__init__.py
dataclasses_avroschema/fields/base.py
dataclasses_avroschema/fields/field_utils.py
dataclasses_avroschema/fields/fields.py
dataclasses_avroschema/fields/mapper.py
dataclasses_avroschema/main.py
dataclasses_avroschema/model_generator/__init__.py
dataclasses_avroschema/model_generator/generator.py
dataclasses_avroschema/model_generator/lang/python/__init__.py
dataclasses_avroschema/model_generator/lang/python/avro_to_python_utils.py
dataclasses_avroschema/model_generator/lang/python/avrodantic/__init__.py
dataclasses_avroschema/model_generator/lang/python/avrodantic/avrodantic_model_generator.py
dataclasses_avroschema/model_generator/lang/python/base.py
dataclasses_avroschema/model_generator/lang/python/dataclasses/__init__.py
dataclasses_avroschema/model_generator/lang/python/dataclasses/dataclass_model_generator.py
dataclasses_avroschema/model_generator/lang/python/pydantic/__init__.py
dataclasses_avroschema/model_generator/lang/python/pydantic/pydantic_model_generator.py
dataclasses_avroschema/model_generator/lang/python/templates.py
dataclasses_avroschema/parser.py
dataclasses_avroschema/protocol.py
dataclasses_avroschema/py.typed
dataclasses_avroschema/pydantic/__init__.py
dataclasses_avroschema/pydantic/fields.py
dataclasses_avroschema/pydantic/main.py
dataclasses_avroschema/pydantic/mapper.py
dataclasses_avroschema/pydantic/parser.py
dataclasses_avroschema/pydantic/v1/__init__.py
dataclasses_avroschema/pydantic/v1/main.py
dataclasses_avroschema/pydantic/v1/mapper.py
dataclasses_avroschema/pydantic/v1/parser.py
dataclasses_avroschema/serialization.py
dataclasses_avroschema/types.py
dataclasses_avroschema/utils.py
dataclasses_avroschema-0.66.2.dist-info/METADATA
dataclasses_avroschema-0.66.2.dist-info/WHEEL
dataclasses_avroschema-0.66.2.dist-info/licenses/LICENSE
dataclasses_avroschema-0.66.2.dist-info/RECORD
