Metadata-Version: 2.4
Name: dataclasses-avroschema
Version: 0.66.2
Summary: Generate Avro Schemas from Python classes. Serialize/Deserialize python instances with avro schemas
License: MIT
License-File: LICENSE
Author: Marcos Schroh
Author-email: schrohm@gmail.com
Requires-Python: >=3.10,<4.0
Classifier: Intended Audience :: Developers
Classifier: License :: OSI Approved :: MIT License
Classifier: Programming Language :: Python :: 3
Classifier: Programming Language :: Python :: 3.10
Classifier: Programming Language :: Python :: 3.11
Classifier: Programming Language :: Python :: 3.12
Classifier: Programming Language :: Python :: 3.13
Classifier: Programming Language :: Python :: 3.14
Classifier: Programming Language :: Python :: 3 :: Only
Classifier: Topic :: Software Development
Provides-Extra: cli
Provides-Extra: faker
Provides-Extra: faust
Provides-Extra: pydantic
Requires-Dist: casefy (>=0.1.7,<1.1.0)
Requires-Dist: dacite (>=1.8.0,<2.0.0)
Requires-Dist: dc-avro (>=0.6.4) ; extra == "cli"
Requires-Dist: faker (>=26.0.0,<38.0.0) ; extra == "faker"
Requires-Dist: fastavro (>=1.7.3,<2.0.0)
Requires-Dist: faust-streaming (>=0.10.11,<0.12.0) ; extra == "faust"
Requires-Dist: inflection (>=0.5.1,<0.6.0)
Requires-Dist: pydantic[email] (>=2.4.2,<3.0.0) ; extra == "pydantic"
Requires-Dist: python-dateutil (>=2.7,<3.0)
Requires-Dist: typing-extensions (>=4.2.0,<5.0.0)
